llm_helper/__init__.py
llm_helper/ai.py
llm_helper/index.py
llm_helper/prompting.py
llm_helper/task.py
llm_helper_tools-0.5.0.dist-info/METADATA
llm_helper_tools-0.5.0.dist-info/WHEEL
llm_helper_tools-0.5.0.dist-info/top_level.txt
llm_helper_tools-0.5.0.dist-info/RECORD
